examples/advanced_usage.py
examples/basic_usage.py
memoravel/__init__.py
memoravel/memoravel.py
source/conf.py
tests/__init__.py
tests/test_memoravel.py
memoravel-1.0.0.dist-info/LICENSE
memoravel-1.0.0.dist-info/METADATA
memoravel-1.0.0.dist-info/WHEEL
memoravel-1.0.0.dist-info/top_level.txt
memoravel-1.0.0.dist-info/RECORD
