Metadata-Version: 2.1
Name: memoravel
Version: 1.0.0
Summary: A library to manage message history, for implementing memory in Language Models.
Home-page: https://github.com/peninha/memoravel
Author: Pena
Author-email: Pena <penadoxo@gmail.com>
License: MIT
Keywords: LLM,memory,message,history
Classifier: Programming Language :: Python :: 3
Classifier: License :: OSI Approved :: MIT License
Classifier: Operating System :: OS Independent
Requires-Python: >=3.7
License-File: LICENSE
Requires-Dist: tiktoken>=0.1
Requires-Dist: jsonschema>=4.0
